scrippy_db/__init__.py
scrippy_db/connector/__init__.py
scrippy_db/connector/mysql/__init__.py
scrippy_db/connector/oracle/__init__.py
scrippy_db/connector/pgsql/__init__.py
scrippy_db/connector/sqlite3/__init__.py
scrippy_db/db/__init__.py
scrippy_db-2.0.1.dist-info/LICENSE
scrippy_db-2.0.1.dist-info/METADATA
scrippy_db-2.0.1.dist-info/WHEEL
scrippy_db-2.0.1.dist-info/top_level.txt
scrippy_db-2.0.1.dist-info/RECORD
